MANIFEST.in
README.rst
setup.cfg
setup.py
traffic_light_simulator/__init__.py
traffic_light_simulator/helpers.py
traffic_light_simulator/models.py
traffic_light_simulator/tests.py
traffic_light_simulator/user_interface.py
traffic_light_simulator.egg-info/PKG-INFO
traffic_light_simulator.egg-info/SOURCES.txt
traffic_light_simulator.egg-info/dependency_links.txt
traffic_light_simulator.egg-info/entry_points.txt
traffic_light_simulator.egg-info/top_level.txt
traffic_light_simulator/light_art/green.txt
traffic_light_simulator/light_art/red.txt
traffic_light_simulator/light_art/yellow.txt