Metadata-Version: 1.1
Name: traffic-light-simulator
Version: 0.1.1
Summary: A Traffic Light Simulator
Home-page: https://github.com/santeyio/traffic-light-simulator
Author: Caleb Hayashida
Author-email: santeyio@gmail.com
License: UNKNOWN
Download-URL: https://github.com/santeyio/traffic-light-simulator/archive/0.1.tar.gz
Keywords: testing,example
Platform: UNKNOWN
